{
  "headline": "KATSEYE Announces 5-Member Comeback Amid Manon Exit Rumors",
  "slides": [
    {
      "image": "https://media.gettyimages.com/id/2233662643/photo/yoonchae-jeong-of-katseye-at-the-mtv-video-music-awards.jpg",
      "line1": "KATSEYE CRISIS",
      "line2": "MANON BANNERMAN",
      "line3": "HIATUS CONTINUES",
      "subtitle": "Member missing from new EP 'WILD' promotional materials"
    },
    {
      "image": "https://media.gettyimages.com/id/2233662644/photo/katseye-group-photo-at-grammy-awards.jpg",
      "line1": "GROUP COMEBACK",
      "line2": "FIVE MEMBERS",
      "line3": "AUGUST RELEASE",
      "subtitle": "EP 'WILD' scheduled for August 14 without Manon"
    },
    {
      "image": "https://media.gettyimages.com/id/2233662645/photo/manon-bannerman-at-coachella-2026.jpg",
      "line1": "COACHELLA DRAMA",
      "line2": "MANON SPOTTED",
      "line3": "IN CROWD ONLY",
      "subtitle": "Watched group perform from audience, not on stage"
    },
    {
      "image": "https://media.gettyimages.com/id/2233662646/photo/katseye-coachella-performance-2026.jpg",
      "line1": "FAN REACTIONS",
      "line2": "EYEKONS ANGRY",
      "line3": "DEMAND ANSWERS",
      "subtitle": "Fans criticize HYBE x Geffen for lack of transparency"
    },
    {
      "image": "https://media.gettyimages.com/id/2233662647/photo/katseye-press-conference-2026.jpg",
      "line1": "FUTURE UNCERTAIN",
      "line2": "SIX OR NOTHING",
      "line3": "FANS WORRIED",
      "subtitle": "Hashtag #SIXORNOTHING trends as fans mourn OT6"
    }
  ]
}